zoomlog/__init__.py
zoomlog/main.py
zoomlog_ZOOM_DEVELOPER-1.0.dist-info/LICENSE
zoomlog_ZOOM_DEVELOPER-1.0.dist-info/METADATA
zoomlog_ZOOM_DEVELOPER-1.0.dist-info/WHEEL
zoomlog_ZOOM_DEVELOPER-1.0.dist-info/top_level.txt
zoomlog_ZOOM_DEVELOPER-1.0.dist-info/RECORD
